microbeads/__init__.py
microbeads/cli.py
microbeads/issues.py
microbeads/merge.py
microbeads/repo.py
microbeads-0.3.0.dist-info/METADATA
microbeads-0.3.0.dist-info/WHEEL
microbeads-0.3.0.dist-info/entry_points.txt
microbeads-0.3.0.dist-info/licenses/LICENSE
microbeads-0.3.0.dist-info/RECORD
