Metadata-Version: 2.4
Name: microbeads
Version: 0.3.0
Summary: A simplified git-backed issue tracker for AI agents
License-File: LICENSE
Requires-Python: >=3.10
Requires-Dist: click>=8.0
Requires-Dist: orjson>=3.9
Provides-Extra: dev
Requires-Dist: pytest-cov>=4.0; extra == 'dev'
Requires-Dist: pytest>=8.0; extra == 'dev'
Requires-Dist: ruff>=0.4; extra == 'dev'
